{"verses":[{"id":7216,"number":1,"words":[["h1961","וַיְהִ֕י",""],["h7093","מִקֵּ֖ץ","And it came to pass at the end"],["h8141","שְׁנָתַ֣יִם","years"],["h3117","יָמִ֑ים","of two full"],["h6547","וּפַרְעֹ֣ה","that Pharaoh"],["h2492","חֹלֵ֔ם","dreamed"],["h2009","וְהִנֵּ֖ה",""],["h5975","עֹמֵ֥ד","and behold he stood"],["h5921","עַל",""],["h2975","הַיְאֹֽר׃","by the river"]]},{"id":7217,"number":2,"words":[["h2009","וְהִנֵּ֣ה",""],["h4480","מִן",""],["h2975","הַיְאֹ֗ר","out of the river"],["h5927","עֹלֹת֙","And behold there came up"],["h7651","שֶׁ֣בַע","seven"],["h6510","פָּר֔וֹת","kine"],["h3303","יְפ֥וֹת","well"],["h4758","מַרְאֶ֖ה","favoured"],["h1277","וּבְרִיאֹ֣ת","and fatfleshed"],["h1320","בָּשָׂ֑ר",""],["h7462","וַתִּרְעֶ֖ינָה","and they fed"],["h260","בָּאָֽחוּ׃","in a meadow"]]},{"id":7218,"number":3,"words":[["h2009","וְהִנֵּ֞ה",""],["h7651","שֶׁ֧בַע","And behold seven"],["h6510","הַפָּר֖וֹת","kine"],["h312","אֲחֵר֗וֹת","other"],["h5927","עֹל֤וֹת","came up"],["h310","אַֽחֲרֵיהֶן֙","after them"],["h4480","מִן",""],["h2975","הַיְאֹֽר׃","of the river"],["h7451","רָע֥וֹת","ill"],["h4758","מַרְאֶ֖ה","favoured"],["h1851","וְדַקּ֣וֹת","and leanfleshed"],["h1320","בָּשָׂ֑ר",""],["h5975","וַֽתַּעֲמֹ֛דְנָה","and stood"],["h681","אֵ֥צֶל","by"],["h5921","עַל",""],["h8193","שְׂפַ֥ת","upon the brink"]]},{"id":7219,"number":4,"words":[["h398","וַתֹּאכַ֣לְנָה","did eat up"],["h6510","הַפָּר֔וֹת","kine"],["h7451","רָע֤וֹת","And the ill"],["h4758","הַמַּרְאֶ֖ה","favoured"],["h1851","וְדַקֹּ֣ת","and leanfleshed"],["h1320","הַבָּשָׂ֔ר",""],["h853","אֵ֚ת",""],["h7651","שֶׁ֣בַע","the seven"],["h3303","יְפֹ֥ת","well"],["h1277","וְהַבְּרִיאֹ֑ת","and fat"],["h3364","וַיִּיקַ֖ץ","awoke"],["h6547","פַּרְעֹֽה׃","So Pharaoh"]]},{"id":7220,"number":5,"words":[["h3462","וַיִּישָׁ֕ן","And he slept"],["h2492","וַֽיַּחֲלֹ֖ם","and dreamed"],["h8145","שֵׁנִ֑ית","the second time"],["h2009","וְהִנֵּ֣ה׀",""],["h7651","שֶׁ֣בַע","and behold seven"],["h7641","שִׁבֳּלִ֗ים","ears of corn"],["h5927","עֹל֛וֹת","came up"],["h7070","בְּקָנֶ֥ה","stalk"],["h259","אֶחָ֖ד","upon one"],["h1277","בְּרִיא֥וֹת","rank"],["h2896","וְטֹבֽוֹת׃","and good"]]},{"id":7221,"number":6,"words":[["h2009","וְהִנֵּה֙",""],["h7651","שֶׁ֣בַע","And behold seven"],["h7641","שִׁבֳּלִ֔ים","ears"],["h1851","דַּקּ֖וֹת","thin"],["h7710","וּשְׁדוּפֹ֣ת","and blasted"],["h6921","קָדִ֑ים","with the east wind"],["h6779","צֹֽמְח֖וֹת","sprung up"],["h310","אַֽחֲרֵיהֶֽן׃","after them"]]},{"id":7222,"number":7,"words":[["h1104","וַתִּבְלַ֙עְנָה֙","devoured"],["h7641","הַֽשִּׁבֳּלִ֔ים","ears"],["h1851","הַדַּקּ֔וֹת","And the seven thin"],["h853","אֵ֚ת",""],["h7651","שֶׁ֣בַע","the seven"],["h1277","הַבְּרִיא֖וֹת","rank"],["h4392","וְהַמְּלֵא֑וֹת","and full"],["h3364","וַיִּיקַ֥ץ","awoke"],["h6547","פַּרְעֹ֖ה","And Pharaoh"],["h2009","וְהִנֵּ֥ה",""],["h2472","חֲלֽוֹם׃","and behold it was a dream"]]},{"id":7223,"number":8,"words":[["h1961","וַיְהִ֤י",""],["h1242","בַבֹּ֙קֶר֙","And it came to pass in the morning"],["h6470","וַתִּפָּ֣עֶם","was troubled"],["h7307","רוּח֔וֹ","that his spirit"],["h7971","וַיִּשְׁלַ֗ח","and he sent"],["h7121","וַיִּקְרָ֛א","and called"],["h853","אֶת",""],["h3605","כָּל",""],["h2748","חַרְטֻמֵּ֥י","for all the magicians"],["h4714","מִצְרַ֖יִם","of Egypt"],["h2450","חֲכָמֶ֑יהָ","and all the wise men"],["h5608","וַיְסַפֵּ֨ר","told"],["h6547","לְפַרְעֹֽה׃","them unto Pharaoh"],["h0","לָהֶם֙",""],["h2472","חֲלֹמ֔וֹ","them his dream"],["h369","וְאֵין",""],["h6622","פּוֹתֵ֥ר","but there was none that could interpret"]]},{"id":7224,"number":9,"words":[["h1696","וַיְדַבֵּר֙","Then spake"],["h8269","שַׂ֣ר","the chief"],["h4945","הַמַּשְׁקִ֔ים",""],["h854","אֶת",""],["h6547","פַּרְעֹ֖ה","unto Pharaoh"],["h559","לֵאמֹ֑ר","saying"],["h853","אֶת",""],["h2399","חֲטָאַ֕י","my faults"],["h589","אֲנִ֖י",""],["h2142","מַזְכִּ֥יר","I do remember"],["h3117","הַיּֽוֹם׃","this day"]]},{"id":7225,"number":10,"words":[["h6547","פַּרְעֹ֖ה","Pharaoh"],["h7107","קָצַ֣ף","was wroth"],["h5921","עַל",""],["h5650","עֲבָדָ֑יו","with his servants"],["h5414","וַיִּתֵּ֨ן","and put"],["h853","אֹתִ֜י",""],["h4929","בְּמִשְׁמַ֗ר","me in ward"],["h1004","בֵּ֚ית","house"],["h8269","שַׂ֥ר","both me and the chief"],["h2876","הַטַּבָּחִ֔ים","of the guard's"],["h644","הָֽאֹפִֽים׃","baker"]]},{"id":7226,"number":11,"words":[["h2492","חָלָֽמְנוּ׃","And we dreamed"],["h2472","חֲלֹמ֖וֹ","a dream"],["h3915","בְּלַ֥יְלָה","night"],["h259","אֶחָ֖ד","in one"],["h589","אֲנִ֣י",""],["h1931","וָה֑וּא",""],["h376","אִ֛ישׁ","each man"],["h6623","כְּפִתְר֥וֹן","according to the interpretation"]]},{"id":7227,"number":12,"words":[["h8033","וְשָׁ֨ם",""],["h854","אִתָּ֜נוּ",""],["h5288","נַ֣עַר","And there was there with us a young man"],["h5680","עִבְרִ֗י","an Hebrew"],["h5650","עֶ֚בֶד","servant"],["h8269","לְשַׂ֣ר","to the captain"],["h2876","הַטַּבָּחִ֔ים","of the guard"],["h5608","וַ֨נְּסַפֶּר","and we told"],["h0","ל֔וֹ",""],["h6622","פָּתָֽר׃","he did interpret"],["h853","אֶת",""],["h2472","כַּֽחֲלֹמ֖וֹ","according to his dream"],["h582","אִ֥ישׁ",""]]},{"id":7228,"number":13,"words":[["h1961","וַיְהִ֛י",""],["h834","כַּֽאֲשֶׁ֥ר",""],["h6622","פָּֽתַר","And it came to pass as he interpreted"],["h0","לָ֖נוּ",""],["h3651","כֵּ֣ן",""],["h853","אֹתִ֛י",""],["h7725","הֵשִׁ֥יב","to us so it was me he restored"],["h5921","עַל",""],["h3653","כַּנִּ֖י","unto mine office"],["h8518","תָלָֽה׃","and him he hanged"]]},{"id":7229,"number":14,"words":[["h7971","וַיִּשְׁלַ֤ח","sent"],["h6547","פַּרְעֹֽה׃","Then Pharaoh"],["h7121","וַיִּקְרָ֣א","and called"],["h853","אֶת",""],["h3130","יוֹסֵ֔ף","Joseph"],["h7323","וַיְרִיצֻ֖הוּ","and they brought him hastily"],["h4480","מִן",""],["h953","הַבּ֑וֹר","out of the dungeon"],["h1548","וַיְגַלַּח֙","and he shaved"],["h2498","וַיְחַלֵּ֣ף","himself and changed"],["h8071","שִׂמְלֹתָ֔יו","his raiment"],["h935","וַיָּבֹ֖א","and came in"],["h413","אֶל",""]]},{"id":7230,"number":15,"words":[["h559","לֵאמֹ֔ר","said"],["h6547","פַּרְעֹה֙","And Pharaoh"],["h413","אֶל",""],["h3130","יוֹסֵ֔ף","unto Joseph"],["h2472","חֲל֖וֹם","a dream"],["h2492","חָלַ֔מְתִּי","I have dreamed"],["h6622","לִפְתֹּ֥ר","and there is none that can interpret"],["h369","אֵ֣ין",""],["h853","אֹת֑וֹ",""],["h589","וַֽאֲנִ֗י",""],["h8085","תִּשְׁמַ֥ע","it and I have heard"],["h5921","עָלֶ֙יךָ֙",""]]},{"id":7231,"number":16,"words":[["h6030","יַֽעֲנֶ֖ה","an answer"],["h3130","יוֹסֵ֧ף","And Joseph"],["h853","אֶת",""],["h6547","פַּרְעֹֽה׃","Pharaoh"],["h559","לֵאמֹ֖ר","saying"],["h1107","בִּלְעָדָ֑י","It is not in me"],["h430","אֱלֹהִ֕ים","God"],["h7965","שְׁל֥וֹם","of peace"]]},{"id":7232,"number":17,"words":[["h1696","וַיְדַבֵּ֥ר","said"],["h6547","פַּרְעֹ֖ה","And Pharaoh"],["h413","אֶל",""],["h3130","יוֹסֵ֑ף","unto Joseph"],["h2472","בַּֽחֲלֹמִ֕י","In my dream"],["h2005","הִנְנִ֥י",""],["h5975","עֹמֵ֖ד","behold I stood"],["h5921","עַל",""],["h8193","שְׂפַ֥ת","upon the bank"],["h2975","הַיְאֹֽר׃","of the river"]]},{"id":7233,"number":18,"words":[["h2009","וְהִנֵּ֣ה",""],["h4480","מִן",""],["h2975","הַיְאֹ֗ר","out of the river"],["h5927","עֹלֹת֙","And behold there came up"],["h7651","שֶׁ֣בַע","seven"],["h6510","פָּר֔וֹת","kine"],["h1277","בְּרִיא֥וֹת","fatfleshed"],["h1320","בָּשָׂ֖ר",""],["h3303","וִיפֹ֣ת","and well"],["h8389","תֹּ֑אַר","favoured"],["h7462","וַתִּרְעֶ֖ינָה","and they fed"],["h260","בָּאָֽחוּ׃","in a meadow"]]},{"id":7234,"number":19,"words":[["h2009","וְהִנֵּ֞ה",""],["h7651","שֶֽׁבַע","And behold seven"],["h6510","פָּר֤וֹת","kine"],["h312","אֲחֵרוֹת֙","other"],["h5927","עֹל֣וֹת","came up"],["h310","אַֽחֲרֵיהֶ֔ן","after them"],["h1803","דַּלּ֨וֹת","poor"],["h7451","וְרָע֥וֹת","ill"],["h8389","תֹּ֛אַר","favoured"],["h3966","מְאֹ֖ד","and very"],["h7534","וְרַקּ֣וֹת","and leanfleshed"],["h1320","בָּשָׂ֑ר",""],["h3808","לֹֽא","as I never"],["h7200","רָאִ֧יתִי","saw"],["h2007","כָהֵ֛נָּה","such"],["h3605","בְּכָל",""],["h776","אֶ֥רֶץ","in all the land"],["h4714","מִצְרַ֖יִם","of Egypt"],["h7455","לָרֹֽעַ׃","for badness"]]},{"id":7235,"number":20,"words":[["h398","וַתֹּאכַ֙לְנָה֙","did eat up"],["h6510","הַפָּר֛וֹת","kine"],["h7534","הָֽרַקּ֖וֹת","And the lean"],["h7451","וְהָֽרָע֑וֹת","and the ill favoured"],["h853","אֵ֣ת",""],["h7651","שֶׁ֧בַע","seven"],["h7223","הָרִֽאשֹׁנ֖וֹת","the first"],["h1277","הַבְּרִיאֹֽת׃","fat"]]},{"id":7236,"number":21,"words":[["h935","בָ֣אוּ","And when they had eaten them up"],["h413","אֶל",""],["h7130","קִרְבֶּ֗נָה",""],["h3808","וְלֹ֤א",""],["h3045","נוֹדַע֙","it could not be known"],["h3588","כִּי",""],["h4758","וּמַרְאֵיהֶ֣ן","but they were still"],["h7451","רַ֔ע","ill favoured"],["h834","כַּֽאֲשֶׁ֖ר",""],["h8462","בַּתְּחִלָּ֑ה","as at the beginning"],["h3364","וָֽאִיקָֽץ׃","So I awoke"]]},{"id":7237,"number":22,"words":[["h7200","וָאֵ֖רֶא","And I saw"],["h2472","בַּֽחֲלֹמִ֑י","in my dream"],["h2009","וְהִנֵּ֣ה׀",""],["h7651","שֶׁ֣בַע","and behold seven"],["h7641","שִׁבֳּלִ֗ים","ears"],["h5927","עֹלֹ֛ת","came up"],["h7070","בְּקָנֶ֥ה","stalk"],["h259","אֶחָ֖ד","in one"],["h4392","מְלֵאֹ֥ת","full"],["h2896","וְטֹבֽוֹת׃","and good"]]},{"id":7238,"number":23,"words":[["h2009","וְהִנֵּה֙",""],["h7651","שֶׁ֣בַע","And behold seven"],["h7641","שִׁבֳּלִ֔ים","ears"],["h6798","צְנֻמ֥וֹת","withered"],["h1851","דַּקּ֖וֹת","thin"],["h7710","שְׁדֻפ֣וֹת","and blasted"],["h6921","קָדִ֑ים","with the east wind"],["h6779","צֹֽמְח֖וֹת","sprung up"],["h310","אַֽחֲרֵיהֶֽם׃","after them"]]},{"id":7239,"number":24,"words":[["h1104","וַתִּבְלַ֙עְןָ֙","devoured"],["h7641","הַֽשִׁבֳּלִ֖ים","ears"],["h1851","הַדַּקֹּ֔ת","And the thin"],["h853","אֵ֛ת",""],["h7651","שֶׁ֥בַע","the seven"],["h2896","הַטֹּב֑וֹת","good"],["h559","וָֽאֹמַר֙","and I told"],["h413","אֶל",""],["h2748","הַֽחַרְטֻמִּ֔ים","this unto the magicians"],["h369","וְאֵ֥ין",""],["h5046","מַגִּ֖יד","but there was none that could declare"],["h0","לִֽי׃",""]]},{"id":7240,"number":25,"words":[["h559","וַיֹּ֤אמֶר","said"],["h3130","יוֹסֵף֙","And Joseph"],["h413","אֶל",""],["h6547","לְפַרְעֹֽה׃","Pharaoh"],["h2472","חֲל֥וֹם","The dream"],["h259","אֶחָ֣ד","is one"],["h1931","ה֑וּא",""],["h853","אֵ֣ת",""],["h834","אֲשֶׁ֧ר",""],["h430","הָֽאֱלֹהִ֛ים","God"],["h6213","עֹשֶׂ֖ה","what he is about to do"],["h5046","הִגִּ֥יד","hath shewed"]]},{"id":7241,"number":26,"words":[["h7651","שֶׁ֥בַע","The seven"],["h6510","פָּרֹ֣ת","kine"],["h2896","הַטֹּבֹ֔ת","good"],["h8141","שָׁנִ֖ים","years"],["h2007","הֵ֔נָּה",""],["h7641","הַֽשִּׁבֳּלִים֙","ears"],["h2472","חֲל֖וֹם","the dream"],["h259","אֶחָ֥ד","is one"],["h1931","הֽוּא׃",""]]},{"id":7242,"number":27,"words":[["h7651","שֶׁ֖בַע","And the seven"],["h6510","הַ֠פָּרוֹת","kine"],["h7534","הָֽרַקּ֨וֹת","thin"],["h7451","וְהָֽרָעֹ֜ת","and ill favoured"],["h5927","הָֽעֹלֹ֣ת","that came up"],["h310","אַֽחֲרֵיהֶ֗ן","after them"],["h8141","שְׁנֵ֥י","years"],["h2007","הֵ֔נָּה",""],["h7641","הַֽשִׁבֳּלִים֙","ears"],["h7386","הָֽרֵק֔וֹת","empty"],["h7710","שְׁדֻפ֖וֹת","blasted"],["h6921","הַקָּדִ֑ים","with the east wind"],["h1961","יִֽהְי֕וּ",""],["h7458","רָעָֽב׃","of famine"]]},{"id":7243,"number":28,"words":[["h1931","ה֣וּא",""],["h1697","הַדָּבָ֔ר","This is the thing"],["h834","אֲשֶׁ֥ר",""],["h1696","דִּבַּ֖רְתִּי","which I have spoken"],["h413","אֶל",""],["h6547","פַּרְעֹֽה׃","unto Pharaoh"],["h430","הָֽאֱלֹהִ֛ים","What God"],["h6213","עֹשֶׂ֖ה","is about to do"],["h7200","הֶרְאָ֥ה","he sheweth"],["h853","אֶת",""]]},{"id":7244,"number":29,"words":[["h2009","הִנֵּ֛ה",""],["h7651","שֶׁ֥בַע","seven"],["h8141","שָׁנִ֖ים","years"],["h935","בָּא֑וֹת","Behold there come"],["h7647","שָׂבָ֥ע","plenty"],["h1419","גָּד֖וֹל","of great"],["h3605","בְּכָל",""],["h776","אֶ֥רֶץ","throughout all the land"],["h4714","מִצְרָֽיִם׃","of Egypt"]]},{"id":7245,"number":30,"words":[["h6965","וְ֠קָמוּ","And there shall arise"],["h7651","שֶׁ֨בַע","seven"],["h8141","שְׁנֵ֤י","years"],["h7458","הָֽרָעָ֖ב","and the famine"],["h310","אַֽחֲרֵיהֶ֔ן","after them"],["h7911","וְנִשְׁכַּ֥ח","shall be forgotten"],["h3605","כָּל",""],["h7647","הַשָּׂבָ֖ע","and all the plenty"],["h776","הָאָֽרֶץ׃","in the land"],["h4714","מִצְרָ֑יִם","of Egypt"],["h3615","וְכִלָּ֥ה","shall consume"],["h853","אֶת",""]]},{"id":7246,"number":31,"words":[["h3808","וְלֹֽא",""],["h3045","יִוָּדַ֤ע","shall not be known"],["h7647","הַשָּׂבָע֙","And the plenty"],["h776","בָּאָ֔רֶץ","in the land"],["h6440","מִפְּנֵ֛י","by reason"],["h7458","הָֽרָעָ֥ב","of that famine"],["h1931","הַה֖וּא",""],["h310","אַֽחֲרֵי","following"],["h3651","כֵ֑ן",""],["h3588","כִּֽי",""],["h3515","כָבֵ֥ד","grievous"],["h3966","מְאֹֽד׃","for it shall be very"]]},{"id":7247,"number":32,"words":[["h5921","וְעַ֨ל",""],["h8138","הִשָּׁנ֧וֹת","was doubled"],["h2472","הַֽחֲל֛וֹם","And for that the dream"],["h413","אֶל",""],["h6547","פַּרְעֹ֖ה","unto Pharaoh"],["h6471","פַּֽעֲמָ֑יִם","twice"],["h3588","כִּֽי",""],["h3559","נָכ֤וֹן","is established"],["h1697","הַדָּבָר֙","it is because the thing"],["h5973","מֵעִ֣ם","by"],["h430","הָֽאֱלֹהִ֖ים","God"],["h4116","וּמְמַהֵ֥ר","will shortly"],["h6213","לַֽעֲשֹׂתֽוֹ׃","bring it to pass"]]},{"id":7248,"number":33,"words":[["h6258","וְעַתָּה֙",""],["h7200","יֵרֶ֣א","look out"],["h6547","פַרְעֹ֔ה","Now therefore let Pharaoh"],["h376","אִ֖ישׁ","a man"],["h995","נָב֣וֹן","discreet"],["h2450","וְחָכָ֑ם","and wise"],["h7896","וִֽישִׁיתֵ֖הוּ","and set"],["h5921","עַל",""],["h776","אֶ֥רֶץ","him over the land"],["h4714","מִצְרָֽיִם׃","of Egypt"]]},{"id":7249,"number":34,"words":[["h6213","יַֽעֲשֶׂ֣ה","do"],["h6547","פַרְעֹ֔ה","Let Pharaoh"],["h6485","וְיַפְקֵ֥ד","this and let him appoint"],["h6496","פְּקִדִ֖ים","officers"],["h5921","עַל",""],["h776","אֶ֣רֶץ","of the land"],["h2567","וְחִמֵּשׁ֙","and take up the fifth part"],["h853","אֶת",""],["h4714","מִצְרַ֔יִם","of Egypt"],["h7651","בְּשֶׁ֖בַע","in the seven"],["h8141","שְׁנֵ֥י","years"],["h7647","הַשָּׂבָֽע׃","plenteous"]]},{"id":7250,"number":35,"words":[["h6908","וְיִקְבְּצ֗וּ","And let them gather"],["h853","אֶת",""],["h3605","כָּל",""],["h400","אֹ֥כֶל","all the food"],["h8141","הַשָּׁנִ֣ים","years"],["h2896","הַטֹּב֔וֹת","of those good"],["h935","הַבָּאֹ֖ת","that come"],["h428","הָאֵ֑לֶּה",""],["h6651","וְיִצְבְּרוּ","and lay up"],["h1250","בָ֞ר","corn"],["h8478","תַּ֧חַת",""],["h3027","יַד","under the hand"],["h6547","פַּרְעֹ֛ה","of Pharaoh"],["h5892","בֶּֽעָרִ֖ים","in the cities"],["h8104","וְשָׁמָֽרוּ׃","and let them keep"]]},{"id":7251,"number":36,"words":[["h1961","וְהָיָ֨ה",""],["h400","הָאֹ֤כֶל","And that food"],["h6487","לְפִקָּדוֹן֙","shall be for store"],["h776","הָאָ֖רֶץ","that the land"],["h7651","לְשֶׁ֙בַע֙","against the seven"],["h8141","שְׁנֵ֣י","years"],["h7458","בָּֽרָעָֽב׃","not through the famine"],["h834","אֲשֶׁ֥ר",""],["h4714","מִצְרָ֑יִם","of Egypt"],["h3808","וְלֹֽא",""],["h3772","תִכָּרֵ֥ת","perish"]]},{"id":7252,"number":37,"words":[["h3190","וַיִּיטַ֥ב","was good"],["h1697","הַדָּבָ֖ר","And the thing"],["h5869","וּבְעֵינֵ֖י","and in the eyes"],["h6547","פַרְעֹ֑ה","of Pharaoh"],["h3605","כָּל",""],["h5650","עֲבָדָֽיו׃","of all his servants"]]},{"id":7253,"number":38,"words":[["h559","וַיֹּ֥אמֶר","said"],["h6547","פַּרְעֹ֖ה","And Pharaoh"],["h413","אֶל",""],["h5650","עֲבָדָ֑יו","unto his servants"],["h4672","הֲנִמְצָ֣א","Can we find"],["h2088","כָזֶ֔ה","such a one as this"],["h376","אִ֕ישׁ","is a man"],["h834","אֲשֶׁ֛ר","in whom"],["h7307","ר֥וּחַ","the Spirit"],["h430","אֱלֹהִ֖ים","of God"],["h0","בּֽוֹ׃",""]]},{"id":7254,"number":39,"words":[["h559","וַיֹּ֤אמֶר","said"],["h6547","פַּרְעֹה֙","And Pharaoh"],["h413","אֶל",""],["h3130","יוֹסֵ֔ף","unto Joseph"],["h310","אַֽחֲרֵ֨י","Forasmuch"],["h3045","הוֹדִ֧יעַ","hath shewed"],["h430","אֱלֹהִ֛ים","as God"],["h853","אֽוֹתְךָ֖",""],["h3605","כָּל",""],["h2063","זֹ֑את",""],["h369","אֵין",""],["h995","נָב֥וֹן","thee all this there is none so discreet"],["h2450","וְחָכָ֖ם","and wise"],["h3644","כָּמֽוֹךָ׃",""]]},{"id":7255,"number":40,"words":[["h859","אַתָּה֙",""],["h1961","תִּֽהְיֶ֣ה","Thou shalt be"],["h5921","עַל",""],["h1004","בֵּיתִ֔י","over my house"],["h6310","פִּ֖יךָ","and according unto thy word"],["h5401","יִשַּׁ֣ק","be ruled"],["h3605","כָּל",""],["h5971","עַמִּ֑י","shall all my people"],["h7535","רַ֥ק",""],["h3678","הַכִּסֵּ֖א","only in the throne"],["h1431","אֶגְדַּ֥ל","will I be greater"],["h4480","מִמֶּֽךָּ׃",""]]},{"id":7256,"number":41,"words":[["h559","וַיֹּ֥אמֶר","said"],["h6547","פַּרְעֹ֖ה","And Pharaoh"],["h413","אֶל",""],["h3130","יוֹסֵ֑ף","unto Joseph"],["h7200","רְאֵה֙","See"],["h5414","נָתַ֣תִּי","I have set"],["h853","אֹֽתְךָ֔",""],["h5921","עַ֖ל",""],["h3605","כָּל",""],["h776","אֶ֥רֶץ","thee over all the land"],["h4714","מִצְרָֽיִם׃","of Egypt"]]},{"id":7257,"number":42,"words":[["h5493","וַיָּ֨סַר","took off"],["h6547","פַּרְעֹ֤ה","And Pharaoh"],["h853","אֶת",""],["h2885","טַבַּעְתּוֹ֙","his ring"],["h5921","מֵעַ֣ל",""],["h3027","יַ֣ד","from his hand"],["h5414","וַיִּתֵּ֥ן","and put"],["h3130","יוֹסֵ֑ף","it upon Joseph's"],["h3847","וַיַּלְבֵּ֤שׁ","and arrayed"],["h899","בִּגְדֵי","him in vestures"],["h8336","שֵׁ֔שׁ","of fine linen"],["h7760","וַיָּ֛שֶׂם","and put"],["h7242","רְבִ֥ד","chain"],["h2091","הַזָּהָ֖ב","a gold"],["h6677","צַוָּארֽוֹ׃","about his neck"]]},{"id":7258,"number":43,"words":[["h7392","וַיַּרְכֵּ֣ב","And he made him to ride"],["h853","אֹת֗וֹ",""],["h4818","בְּמִרְכֶּ֤בֶת","chariot"],["h4932","הַמִּשְׁנֶה֙","in the second"],["h834","אֲשֶׁר",""],["h0","ל֔וֹ",""],["h7121","וַיִּקְרְא֥וּ","which he had and they cried"],["h6440","לְפָנָ֖יו","before him"],["h86","אַבְרֵ֑ךְ","Bow the knee"],["h5414","וְנָת֣וֹן","and he made"],["h5921","עַ֖ל",""],["h3605","כָּל",""],["h776","אֶ֥רֶץ","him ruler over all the land"],["h4714","מִצְרָֽיִם׃","of Egypt"]]},{"id":7259,"number":44,"words":[["h559","וַיֹּ֧אמֶר","said"],["h6547","פַרְעֹ֑ה","And Pharaoh"],["h413","אֶל",""],["h3130","יוֹסֵ֖ף","unto Joseph"],["h589","אֲנִ֣י",""],["h1107","וּבִלְעָדֶ֗יךָ","and without"],["h3808","לֹֽא",""],["h7311","יָרִ֨ים","lift up"],["h376","אִ֧ישׁ","thee shall no man"],["h853","אֶת",""],["h3027","יָד֛וֹ","his hand"],["h7272","רַגְל֖וֹ","or foot"],["h3605","בְּכָל",""],["h776","אֶ֥רֶץ","in all the land"],["h4714","מִצְרָֽיִם׃","of Egypt"]]},{"id":7260,"number":45,"words":[["h7121","וַיִּקְרָ֨א","called"],["h6547","פַרְעֹ֣ה","And Pharaoh"],["h8034","שֵׁם","name"],["h3130","יוֹסֵ֖ף","And Joseph"],["h0","צָֽפְנַ֣ת",""],["h6847","פַּעְנֵחַ֒","Zaphnathpaaneah"],["h5414","וַיִּתֶּן","and he gave"],["h853","אֶת",""],["h621","אָֽסְנַ֗ת","Asenath"],["h1323","בַּת","the daughter"],["h6319","פֶ֛רַע","of Potipherah"],["h3548","כֹּהֵ֥ן","priest"],["h204","אֹ֖ן","of On"],["h802","לְאִשָּׁ֑ה","him to wife"],["h3318","וַיֵּצֵ֥א","went out"],["h5921","עַל",""],["h776","אֶ֥רֶץ","over all the land"],["h4714","מִצְרָֽיִם׃","of Egypt"]]},{"id":7261,"number":46,"words":[["h3130","יוֹסֵף֙","And Joseph"],["h1121","בֶּן","old"],["h7970","שְׁלֹשִׁ֣ים","was thirty"],["h8141","שָׁנָ֔ה","years"],["h5975","בְּעָמְד֕וֹ","when he stood"],["h6440","מִלִּפְנֵ֣י","before"],["h6547","פַרְעֹ֔ה","Pharaoh"],["h4428","מֶֽלֶךְ","king"],["h4714","מִצְרָֽיִם׃","of Egypt"],["h3318","וַיֵּצֵ֤א","went out"],["h5674","וַֽיַּעְבֹ֖ר","and went throughout"],["h3605","בְּכָל",""],["h776","אֶ֥רֶץ","all the land"]]},{"id":7262,"number":47,"words":[["h6213","וַתַּ֣עַשׂ","brought forth"],["h776","הָאָ֔רֶץ","the earth"],["h7651","בְּשֶׁ֖בַע","And in the seven"],["h8141","שְׁנֵ֣י","years"],["h7647","הַשָּׂבָ֑ע","plenteous"],["h7062","לִקְמָצִֽים׃","by handfuls"]]},{"id":7263,"number":48,"words":[["h6908","וַיִּקְבֹּ֞ץ","And he gathered up"],["h853","אֶת",""],["h3605","כָּל",""],["h400","אֹ֧כֶל","all the food"],["h7651","שֶׁ֣בַע","of the seven"],["h8141","שָׁנִ֗ים","years"],["h834","אֲשֶׁ֤ר",""],["h1961","הָיוּ֙",""],["h776","בְּאֶ֣רֶץ","which were in the land"],["h4714","מִצְרַ֔יִם","of Egypt"],["h5414","נָתַ֥ן","and laid up"],["h5892","הָעִ֛יר","every city"],["h7704","שְׂדֵה","of the field"],["h5439","סְבִֽיבֹתֶ֖יהָ","which was round about"],["h8432","בְּתוֹכָֽהּ׃","in the same"]]},{"id":7264,"number":49,"words":[["h6651","וַיִּצְבֹּ֨ר","gathered"],["h3130","יוֹסֵ֥ף","And Joseph"],["h1250","בָּ֛ר","corn"],["h2344","כְּח֥וֹל","as the sand"],["h3220","הַיָּ֖ם","of the sea"],["h7235","הַרְבֵּ֣ה","much"],["h3966","מְאֹ֑ד","very"],["h5704","עַ֛ד",""],["h3588","כִּֽי",""],["h2308","חָדַ֥ל","until he left"],["h5608","לִסְפֹּ֖ר","numbering"],["h369","אֵ֥ין","for it was without"],["h4557","מִסְפָּֽר׃","number"]]},{"id":7265,"number":50,"words":[["h3130","וּלְיוֹסֵ֤ף","And unto Joseph"],["h3205","יָֽלְדָה","bare"],["h8147","שְׁנֵ֣י","two"],["h1121","בָנִ֔ים","sons"],["h2962","בְּטֶ֥רֶם",""],["h935","תָּב֖וֹא","came"],["h8141","שְׁנַ֣ת","before the years"],["h7458","הָֽרָעָ֑ב","of famine"],["h834","אֲשֶׁ֤ר",""],["h0","לּוֹ֙",""],["h621","אָֽסְנַ֔ת","which Asenath"],["h1323","בַּת","the daughter"],["h6319","פֶ֖רַע","of Potipherah"],["h3548","כֹּהֵ֥ן","priest"],["h204","אֽוֹן׃","of On"]]},{"id":7266,"number":51,"words":[["h7121","וַיִּקְרָ֥א","called"],["h3130","יוֹסֵ֛ף","And Joseph"],["h853","אֶת",""],["h8034","שֵׁ֥ם","the name"],["h1060","הַבְּכ֖וֹר","of the firstborn"],["h4519","מְנַשֶּׁ֑ה","Manasseh"],["h3588","כִּֽי",""],["h5382","נַשַּׁ֤נִי","said he hath made me forget"],["h430","אֱלֹהִים֙","For God"],["h3605","כָּל",""],["h5999","עֲמָלִ֔י","all my toil"],["h1004","בֵּ֥ית","house"],["h1","אָבִֽי׃","and all my father's"]]},{"id":7267,"number":52,"words":[["h853","וְאֵ֛ת",""],["h8034","שֵׁ֥ם","And the name"],["h8145","הַשֵּׁנִ֖י","of the second"],["h7121","קָרָ֣א","called"],["h669","אֶפְרָ֑יִם","he Ephraim"],["h3588","כִּֽי",""],["h6509","הִפְרַ֥נִי","hath caused me to be fruitful"],["h430","אֱלֹהִ֖ים","For God"],["h776","בְּאֶ֥רֶץ","in the land"],["h6040","עָנְיִֽי׃","of my affliction"]]},{"id":7268,"number":53,"words":[["h3615","וַתִּכְלֶ֕ינָה","were ended"],["h7651","שֶׁ֖בַע","And the seven"],["h8141","שְׁנֵ֣י","years"],["h7647","הַשָּׂבָ֑ע","of plenteousness"],["h834","אֲשֶׁ֥ר",""],["h1961","הָיָ֖ה",""],["h776","בְּאֶ֥רֶץ","that was in the land"],["h4714","מִצְרָֽיִם׃","of Egypt"]]},{"id":7269,"number":54,"words":[["h2490","וַתְּחִלֶּ֜ינָה","began"],["h7651","שֶׁ֣בַע","And the seven"],["h8141","שְׁנֵ֤י","years"],["h7458","רָעָב֙","and the dearth"],["h935","לָב֔וֹא","to come"],["h834","כַּֽאֲשֶׁ֖ר",""],["h559","אָמַ֣ר","had said"],["h3130","יוֹסֵ֑ף","according as Joseph"],["h1961","וַיְהִ֤י",""],["h3605","בְּכָל",""],["h776","אֶ֥רֶץ","but in all the land"],["h4714","מִצְרַ֖יִם","of Egypt"],["h3899","לָֽחֶם׃","there was bread"]]},{"id":7270,"number":55,"words":[["h7456","וַתִּרְעַב֙","was famished"],["h3605","כָּל",""],["h776","אֶ֣רֶץ","And when all the land"],["h4714","מִצְרַ֙יִם֙","of Egypt"],["h6817","וַיִּצְעַ֥ק","cried"],["h5971","הָעָ֛ם","the people"],["h413","אֶל",""],["h6547","פַּרְעֹ֤ה","and Pharaoh"],["h3899","לַלָּ֑חֶם","for bread"],["h559","יֹאמַ֥ר","said"],["h1980","לְכ֣וּ",""],["h3130","יוֹסֵ֔ף","unto Joseph"],["h834","אֲשֶׁר",""],["h0","לָכֶ֖ם",""],["h6213","תַּֽעֲשֽׂוּ׃","to you do"]]},{"id":7271,"number":56,"words":[["h7458","הָֽרָעָ֖ב","And the famine"],["h1961","הָיָ֔ה",""],["h5921","עַ֖ל",""],["h3605","כָּל",""],["h6440","פְּנֵ֣י","was over all the face"],["h776","בְּאֶ֥רֶץ","in the land"],["h6605","וַיִּפְתַּ֨ח","opened"],["h3130","יוֹסֵ֜ף","And Joseph"],["h853","אֶֽת",""],["h834","אֲשֶׁ֤ר",""],["h0","בָּהֶם֙",""],["h7666","וַיִּשְׁבֹּ֣ר","all the storehouses and sold"],["h4713","לְמִצְרַ֔יִם",""],["h2388","וַיֶּֽחֱזַ֥ק","waxed sore"],["h4714","מִצְרָֽיִם׃","of Egypt"]]},{"id":7272,"number":57,"words":[["h3605","וְכָל",""],["h776","הָאָֽרֶץ׃","And all countries"],["h935","בָּ֣אוּ","came"],["h4714","מִצְרַ֔יְמָה","into Egypt"],["h7666","לִשְׁבֹּ֖ר","for to buy"],["h413","אֶל",""],["h3130","יוֹסֵ֑ף","to Joseph"],["h3588","כִּֽי",""],["h2388","חָזַ֥ק","was so sore"],["h7458","הָֽרָעָ֖ב","corn because that the famine"]]}]}