{"verses":[{"id":24329,"number":1,"words":[["h1945","ה֧וֹי","Woe"],["h2803","חֹֽשְׁבֵי","to them that devise"],["h205","אָ֛וֶן","iniquity"],["h6466","וּפֹ֥עֲלֵי","and work"],["h7451","רָ֖ע","evil"],["h5921","עַל",""],["h4904","מִשְׁכְּבוֹתָ֑ם","upon their beds"],["h216","בְּא֤וֹר","is light"],["h1242","הַבֹּ֙קֶר֙","when the morning"],["h6213","יַעֲשׂ֔וּהָ","they practise"],["h3588","כִּ֥י",""],["h3426","יֶשׁ","it because it is"],["h410","לְאֵ֖ל","in the power"],["h3027","יָדָֽם׃","of their hand"]]},{"id":24330,"number":2,"words":[["h2530","וְחָמְד֤וּ","And they covet"],["h7704","שָׂדוֹת֙","fields"],["h1497","וְגָזָ֔לוּ","and take them by violence"],["h1004","וּבֵית֔וֹ","and his house"],["h5375","וְנָשָׂ֑אוּ","and take them away"],["h6231","וְעָֽשְׁקוּ֙","so they oppress"],["h1397","גֶּ֣בֶר","a man"],["h376","וְאִ֖ישׁ","even a man"],["h5159","וְנַחֲלָתֽוֹ׃","and his heritage"]]},{"id":24331,"number":3,"words":[["h3651","לָכֵ֗ן",""],["h3541","כֹּ֚ה",""],["h559","אָמַ֣ר","Therefore thus saith"],["h3068","יְהוָ֔ה","the LORD"],["h2005","הִנְנִ֥י",""],["h2803","חֹשֵׁ֛ב","do I devise"],["h5921","עַל",""],["h4940","הַמִּשְׁפָּחָ֥ה","Behold against this family"],["h2063","הַזֹּ֖את",""],["h7451","רָעָ֖ה","an evil"],["h834","אֲ֠שֶׁר",""],["h3808","לֹֽא",""],["h4185","תָמִ֨ישׁוּ","from which ye shall not remove"],["h8033","מִשָּׁ֜ם",""],["h6677","צַוְּארֹֽתֵיכֶ֗ם","your necks"],["h1980","תֵֽלְכוּ֙",""],["h7317","רוֹמָ֔ה","haughtily"],["h3588","כִּ֛י",""],["h6256","עֵ֥ת","for this time"],["h1931","הִֽיא׃",""]]},{"id":24332,"number":4,"words":[["h3117","בַּיּ֨וֹם","In that day"],["h1931","הַה֜וּא",""],["h5375","יִשָּׂ֧א","shall one take up"],["h5921","עֲלֵיכֶ֣ם",""],["h4912","מָשָׁ֗ל","a parable"],["h5091","וְנָהָ֨ה","against you and lament"],["h5092","נְהִ֤י","lamentation"],["h5093","נִֽהְיָה֙","with a doleful"],["h559","אָמַר֙","and say"],["h7703","נְשַׁדֻּ֔נוּ","We be utterly"],["h2506","חֵ֥לֶק","the portion"],["h5971","עַמִּ֖י","of my people"],["h4171","יָמִ֑יר","he hath changed"],["h349","אֵ֚יךְ",""],["h4185","יָמִ֣ישׁ","how hath he removed"],["h0","לִ֔י",""],["h7728","לְשׁוֹבֵ֥ב",""],["h7704","שָׂדֵ֖ינוּ","our fields"],["h2505","יְחַלֵּֽק׃","he hath divided"]]},{"id":24333,"number":5,"words":[["h3651","לָכֵן֙",""],["h3808","לֹֽא",""],["h1961","יִֽהְיֶ֣ה",""],["h0","לְךָ֔",""],["h7993","מַשְׁלִ֥יךְ","Therefore thou shalt have none that shall cast"],["h2256","חֶ֖בֶל","a cord"],["h1486","בְּגוֹרָ֑ל","by lot"],["h6951","בִּקְהַ֖ל","in the congregation"],["h3068","יְהוָֽה׃","of the LORD"]]},{"id":24334,"number":6,"words":[["h408","אַל",""],["h5197","יַטִּ֣פוּ","Prophesy"],["h3808","לֹֽא",""],["h428","לָאֵ֔לֶּה",""],["h5253","יִסַּ֖ג","to them that they shall not take"],["h3639","כְּלִמּֽוֹת׃","shame"]]},{"id":24335,"number":7,"words":[["h559","הֶאָמ֣וּר","O thou that art named"],["h1004","בֵּֽית","the house"],["h3290","יַעֲקֹ֗ב","of Jacob"],["h7114","הֲקָצַר֙","straitened"],["h7307","ר֣וּחַ","is the spirit"],["h3068","יְהוָ֔ה","of the LORD"],["h518","אִם",""],["h428","אֵ֖לֶּה",""],["h4611","מַעֲלָלָ֑יו","are these his doings"],["h3808","הֲל֤וֹא",""],["h1697","דְבָרַ֨י","do not my words"],["h3190","יֵיטִ֔יבוּ","do good"],["h5973","עִ֖ם",""],["h3477","הַיָּשָׁ֥ר","uprightly"],["h1980","הוֹלֵֽךְ׃","to him that walketh"]]},{"id":24336,"number":8,"words":[["h865","וְאֶתְמ֗וּל","Even of late"],["h5971","עַמִּי֙","my people"],["h341","לְאוֹיֵ֣ב","as an enemy"],["h6965","יְקוֹמֵ֔ם","is risen up"],["h4136","מִמּ֣וּל","with"],["h8008","שַׂלְמָ֔ה","the garment"],["h145","אֶ֖דֶר","the robe"],["h6584","תַּפְשִׁט֑וּן","ye pull off"],["h5674","מֵעֹבְרִ֣ים","from them that pass"],["h983","בֶּ֔טַח","by securely"],["h7725","שׁוּבֵ֖י","as men averse"],["h4421","מִלְחָמָֽה׃","from war"]]},{"id":24337,"number":9,"words":[["h802","נְשֵׁ֤י","The women"],["h5971","עַמִּי֙","of my people"],["h1644","תְּגָ֣רְשׁ֔וּן","have ye cast out"],["h1004","מִבֵּ֖ית","houses"],["h8588","תַּֽעֲנֻגֶ֑יהָ","from their pleasant"],["h5921","מֵעַל֙",""],["h5768","עֹֽלָלֶ֔יהָ","from their children"],["h3947","תִּקְח֥וּ","have ye taken away"],["h1926","הֲדָרִ֖י","my glory"],["h5769","לְעוֹלָֽם׃","for ever"]]},{"id":24338,"number":10,"words":[["h6965","ק֣וּמוּ","Arise"],["h1980","וּלְכ֔וּ",""],["h3588","כִּ֥י",""],["h3808","לֹא",""],["h2063","זֹ֖את",""],["h4496","הַמְּנוּחָ֑ה","for this is not your rest"],["h5668","בַּעֲב֥וּר",""],["h2930","טָמְאָ֛ה","because it is polluted"],["h2254","תְּחַבֵּ֖ל","it shall destroy"],["h2256","וְחֶ֥בֶל","destruction"],["h4834","נִמְרָֽץ׃","you even with a sore"]]},{"id":24339,"number":11,"words":[["h3863","לוּ","If"],["h376","אִ֞ישׁ","a man"],["h1980","הֹלֵ֥ךְ","walking"],["h7307","ר֙וּחַ֙","in the spirit"],["h8267","וָשֶׁ֣קֶר","and falsehood"],["h3576","כִּזֵּ֔ב","do lie"],["h5197","מַטִּ֖יף","he shall even be the prophet"],["h0","לְךָ֔",""],["h3196","לַיַּ֖יִן","unto thee of wine"],["h7941","וְלַשֵּׁכָ֑ר","and of strong drink"],["h1961","וְהָיָ֥ה",""],["h5971","הָעָ֥ם","of this people"],["h2088","הַזֶּֽה׃",""]]},{"id":24340,"number":12,"words":[["h622","אֶאֱסֹ֜ף","I will surely"],["h3290","יַעֲקֹ֣ב","O Jacob"],["h3605","כֻּלָּ֗ךְ",""],["h6908","אֲקַבֵּץ֙","all of thee I will surely"],["h7611","שְׁאֵרִ֣ית","the remnant"],["h3478","יִשְׂרָאֵ֔ל","of Israel"],["h3162","יַ֥חַד","them together"],["h7760","אֲשִׂימֶ֖נּוּ","I will put"],["h6629","כְּצֹ֣אן","as the sheep"],["h1223","בָּצְרָ֑ה","of Bozrah"],["h5739","כְּעֵ֙דֶר֙","as the flock"],["h8432","בְּת֣וֹךְ","in the midst"],["h1699","הַדָּֽבְר֔וֹ","of their fold"],["h1949","תְּהִימֶ֖נָה","they shall make great noise"],["h120","מֵאָדָֽם׃","by reason of the multitude of men"]]},{"id":24341,"number":13,"words":[["h5927","עָלָ֤ה","is come up"],["h6555","פָּֽרְצוּ֙","The breaker"],["h6440","לִפְנֵיהֶ֔ם","before"],["h5674","וַיַּעֲבֹ֤ר","and have passed through"],["h8179","שַׁ֖עַר","the gate"],["h3318","וַיֵּ֣צְאוּ","and are gone out"],["h0","ב֑וֹ",""],["h4428","מַלְכָּם֙","by it and their king"],["h3068","וַיהוָ֖ה","them and the LORD"],["h7218","בְּרֹאשָֽׁם׃","on the head"]]}]}